[
    {"id": 0,  "name": "Forge",              "requiredDistrict": "Industrial",  "productionCost": 60,  "maintenanceCost": 1, "productionBonus": 2, "scienceBonus": 0,  "goldBonus": 0, "scienceMultiplier": 1.0},
    {"id": 1,  "name": "Workshop",           "requiredDistrict": "Industrial",  "productionCost": 40,  "maintenanceCost": 1, "productionBonus": 1, "scienceBonus": 0,  "goldBonus": 0, "scienceMultiplier": 1.0},
    {"id": 2,  "name": "Refinery",           "requiredDistrict": "Industrial",  "productionCost": 100, "maintenanceCost": 2, "productionBonus": 3, "scienceBonus": 0,  "goldBonus": 0, "scienceMultiplier": 1.0},
    {"id": 3,  "name": "Factory",            "requiredDistrict": "Industrial",  "productionCost": 120, "maintenanceCost": 3, "productionBonus": 4, "scienceBonus": 0,  "goldBonus": 1, "scienceMultiplier": 1.0},
    {"id": 4,  "name": "Electronics Plant",  "requiredDistrict": "Industrial",  "productionCost": 180, "maintenanceCost": 4, "productionBonus": 3, "scienceBonus": 2,  "goldBonus": 2, "scienceMultiplier": 1.0},
    {"id": 5,  "name": "Industrial Complex", "requiredDistrict": "Industrial",  "productionCost": 250, "maintenanceCost": 5, "productionBonus": 6, "scienceBonus": 0,  "goldBonus": 3, "scienceMultiplier": 1.0},
    {"id": 6,  "name": "Market",             "requiredDistrict": "Commercial",  "productionCost": 50,  "maintenanceCost": 0, "productionBonus": 0, "scienceBonus": 0,  "goldBonus": 3, "scienceMultiplier": 1.0},
    {"id": 7,  "name": "Library",            "requiredDistrict": "Campus",      "productionCost": 90,  "maintenanceCost": 1, "productionBonus": 0, "scienceBonus": 3,  "goldBonus": 0, "scienceMultiplier": 1.0},
    {"id": 8,  "name": "Textile Mill",       "requiredDistrict": "Industrial",  "productionCost": 80,  "maintenanceCost": 2, "productionBonus": 2, "scienceBonus": 0,  "goldBonus": 1, "scienceMultiplier": 1.0},
    {"id": 9,  "name": "Food Proc. Plant",   "requiredDistrict": "Industrial",  "productionCost": 90,  "maintenanceCost": 2, "productionBonus": 1, "scienceBonus": 0,  "goldBonus": 1, "scienceMultiplier": 1.0},
    {"id": 10, "name": "Precision Workshop", "requiredDistrict": "Industrial",  "productionCost": 140, "maintenanceCost": 3, "productionBonus": 3, "scienceBonus": 1,  "goldBonus": 0, "scienceMultiplier": 1.0},
    {"id": 11, "name": "Semiconductor Fab",  "requiredDistrict": "Industrial",  "productionCost": 220, "maintenanceCost": 5, "productionBonus": 2, "scienceBonus": 3,  "goldBonus": 2, "scienceMultiplier": 1.0},
    {"id": 12, "name": "Research Lab",       "requiredDistrict": "Campus",      "productionCost": 480, "maintenanceCost": 3, "productionBonus": 0, "scienceBonus": 10, "goldBonus": 0, "scienceMultiplier": 1.5},
    {"id": 13, "name": "Telecom Hub",        "requiredDistrict": "Commercial",  "productionCost": 130, "maintenanceCost": 2, "productionBonus": 0, "scienceBonus": 1,  "goldBonus": 4, "scienceMultiplier": 1.0},
    {"id": 14, "name": "Airport",            "requiredDistrict": "Industrial",  "productionCost": 200, "maintenanceCost": 4, "productionBonus": 2, "scienceBonus": 0,  "goldBonus": 3, "scienceMultiplier": 1.0},
    {"id": 15, "name": "Granary",            "requiredDistrict": "CityCenter",  "productionCost": 40,  "maintenanceCost": 1, "productionBonus": 1, "scienceBonus": 0,  "goldBonus": 0, "scienceMultiplier": 1.0},
    {"id": 16, "name": "Monument",           "requiredDistrict": "CityCenter",  "productionCost": 30,  "maintenanceCost": 0, "productionBonus": 0, "scienceBonus": 0,  "goldBonus": 0, "scienceMultiplier": 1.0},
    {"id": 17, "name": "Walls",              "requiredDistrict": "Encampment",  "productionCost": 60,  "maintenanceCost": 0, "productionBonus": 0, "scienceBonus": 0,  "goldBonus": 0, "scienceMultiplier": 1.0},
    {"id": 18, "name": "Barracks",           "requiredDistrict": "Encampment",  "productionCost": 70,  "maintenanceCost": 1, "productionBonus": 0, "scienceBonus": 0,  "goldBonus": 0, "scienceMultiplier": 1.0},
    {"id": 19, "name": "University",         "requiredDistrict": "Campus",      "productionCost": 250, "maintenanceCost": 2, "productionBonus": 0, "scienceBonus": 6,  "goldBonus": 0, "scienceMultiplier": 1.0},
    {"id": 20, "name": "Bank",               "requiredDistrict": "Commercial",  "productionCost": 100, "maintenanceCost": 0, "productionBonus": 0, "scienceBonus": 0,  "goldBonus": 5, "scienceMultiplier": 1.0},
    {"id": 21, "name": "Stock Exchange",     "requiredDistrict": "Commercial",  "productionCost": 200, "maintenanceCost": 0, "productionBonus": 0, "scienceBonus": 0,  "goldBonus": 8, "scienceMultiplier": 1.0},
    {"id": 22, "name": "Hospital",           "requiredDistrict": "CityCenter",  "productionCost": 150, "maintenanceCost": 2, "productionBonus": 0, "scienceBonus": 0,  "goldBonus": 0, "scienceMultiplier": 1.0},
    {"id": 23, "name": "Shipyard",           "requiredDistrict": "Harbor",      "productionCost": 120, "maintenanceCost": 2, "productionBonus": 3, "scienceBonus": 0,  "goldBonus": 2, "scienceMultiplier": 1.0},
    {"id": 24, "name": "Mint",               "requiredDistrict": "Commercial",  "productionCost": 70,  "maintenanceCost": 1, "productionBonus": 0, "scienceBonus": 0,  "goldBonus": 2, "scienceMultiplier": 1.0},
    {"id": 25, "name": "Waste Treatment",    "requiredDistrict": "Industrial",  "productionCost": 100, "maintenanceCost": 2, "productionBonus": 0, "scienceBonus": 0,  "goldBonus": 0, "scienceMultiplier": 1.0},
    {"id": 26, "name": "Coal Plant",         "requiredDistrict": "Industrial",  "productionCost": 80,  "maintenanceCost": 2, "productionBonus": 0, "scienceBonus": 0,  "goldBonus": 0, "scienceMultiplier": 1.0},
    {"id": 27, "name": "Oil Plant",          "requiredDistrict": "Industrial",  "productionCost": 120, "maintenanceCost": 3, "productionBonus": 0, "scienceBonus": 0,  "goldBonus": 0, "scienceMultiplier": 1.0},
    {"id": 28, "name": "Hydroelectric Dam",  "requiredDistrict": "Industrial",  "productionCost": 150, "maintenanceCost": 1, "productionBonus": 0, "scienceBonus": 0,  "goldBonus": 0, "scienceMultiplier": 1.0},
    {"id": 29, "name": "Nuclear Plant",      "requiredDistrict": "Industrial",  "productionCost": 300, "maintenanceCost": 5, "productionBonus": 0, "scienceBonus": 0,  "goldBonus": 0, "scienceMultiplier": 1.0},
    {"id": 30, "name": "Solar Array",        "requiredDistrict": "Industrial",  "productionCost": 200, "maintenanceCost": 1, "productionBonus": 0, "scienceBonus": 1,  "goldBonus": 0, "scienceMultiplier": 1.0},
    {"id": 31, "name": "Wind Farm",          "requiredDistrict": "Industrial",  "productionCost": 160, "maintenanceCost": 1, "productionBonus": 0, "scienceBonus": 0,  "goldBonus": 0, "scienceMultiplier": 1.0}
]
